property_driven_ml/__init__.py
property_driven_ml/cli.py
property_driven_ml/constraints/__init__.py
property_driven_ml/constraints/constraints.py
property_driven_ml/constraints/postconditions.py
property_driven_ml/constraints/preconditions.py
property_driven_ml/logics/__init__.py
property_driven_ml/logics/boolean_logic.py
property_driven_ml/logics/dl2.py
property_driven_ml/logics/fuzzy_logics.py
property_driven_ml/logics/logic.py
property_driven_ml/logics/stl.py
property_driven_ml/training/__init__.py
property_driven_ml/training/attacks.py
property_driven_ml/training/engine.py
property_driven_ml/training/epoch_info.py
property_driven_ml/training/grad_norm.py
property_driven_ml/utils/__init__.py
property_driven_ml/utils/safe_eval.py
property_driven_ml/utils/util.py
property_driven_ml/utils/visualization.py
property_driven_ml-0.2.7.dist-info/licenses/LICENSE
property_driven_ml-0.2.7.dist-info/METADATA
property_driven_ml-0.2.7.dist-info/WHEEL
property_driven_ml-0.2.7.dist-info/top_level.txt
property_driven_ml-0.2.7.dist-info/RECORD
