Metadata-Version: 2.4
Name: property-driven-ml
Version: 0.2.7
Summary: A general framework for property-driven machine learning with logical constraints
Author: Thomas Flinkow, Gusts Gustavs Grinbergs
Maintainer: Thomas Flinkow, Gusts Gustavs Grinbergs
License-Expression: MIT
Project-URL: Homepage, https://github.com/ggustavs/property-driven-ml
Project-URL: Repository, https://github.com/ggustavs/property-driven-ml
Project-URL: Bug Tracker, https://github.com/ggustavs/property-driven-ml/issues
Project-URL: Documentation, https://github.com/ggustavs/property-driven-ml#readme
Keywords: machine learning,property driven,constraints,fuzzy logic,adversarial training,neural networks,pytorch
Classifier: Development Status :: 3 - Alpha
Classifier: Intended Audience :: Science/Research
Classifier: Intended Audience :: Developers
Classifier: Programming Language :: Python :: 3
Classifier: Programming Language :: Python :: 3.11
Classifier: Programming Language :: Python :: 3.12
Classifier: Programming Language :: Python :: 3.13
Classifier: Topic :: Scientific/Engineering :: Artificial Intelligence
Classifier: Topic :: Software Development :: Libraries :: Python Modules
Classifier: Operating System :: OS Independent
Requires-Python: >=3.11
License-File: LICENSE
Requires-Dist: idx2numpy>=1.2.3
Requires-Dist: numpy>=2.3.2
Requires-Dist: onnx>=1.18.0
Requires-Dist: onnxruntime>=1.22.1
Requires-Dist: pandas>=2.3.1
Requires-Dist: torch>=2.5.1
Requires-Dist: torchvision>=0.17.0
Provides-Extra: dev
Requires-Dist: pytest>=7.0; extra == "dev"
Requires-Dist: pytest-cov>=4.0; extra == "dev"
Requires-Dist: black>=22.0; extra == "dev"
Requires-Dist: flake8>=5.0; extra == "dev"
Requires-Dist: mypy>=1.0; extra == "dev"
Requires-Dist: twine>=6.1.0; extra == "dev"
Dynamic: license-file
